humancompatible/__init__.py
humancompatible/train/__init__.py
humancompatible/train/benchmark/__init__.py
humancompatible/train/benchmark/algorithms/Algorithm.py
humancompatible/train/benchmark/algorithms/__init__.py
humancompatible/train/benchmark/algorithms/ghost.py
humancompatible/train/benchmark/algorithms/sgd.py
humancompatible/train/benchmark/algorithms/ssl_alm.py
humancompatible/train/benchmark/algorithms/switching_subgradient.py
humancompatible/train/benchmark/algorithms/utils.py
humancompatible/train/benchmark/constraints/__init__.py
humancompatible/train/benchmark/constraints/constraint.py
humancompatible/train/benchmark/constraints/constraint_fns.py
humancompatible/train/benchmark/constraints/torch/__init__.py
humancompatible/train/benchmark/constraints/torch/constraints.py
humancompatible/train/fairness/__init__.py
humancompatible/train/fairness/utils/__init__.py
humancompatible/train/fairness/utils/balanced_batch_sampler.py
humancompatible/train/optim/__init__.py
humancompatible/train/optim/ssl_alm.py
humancompatible/train/optim/ssl_alm_adam.py
humancompatible/train/optim/ssw.py
humancompatible_train-0.1.8.5.dist-info/licenses/LICENCE.txt
humancompatible_train-0.1.8.5.dist-info/METADATA
humancompatible_train-0.1.8.5.dist-info/WHEEL
humancompatible_train-0.1.8.5.dist-info/top_level.txt
humancompatible_train-0.1.8.5.dist-info/RECORD
