Metadata-Version: 2.4
Name: humancompatible-train
Version: 0.1.8.5
Summary: PyTorch-based package for constrained training of neural networks
Author: Gilles Bareilles, Jana Lepsova, Jakub Marecek
Author-email: Andrii Kliachkin <kliachkin.andrii@gmail.com>
Maintainer-email: Andrii Kliachkin <kliachkin.andrii@gmail.com>
Requires-Python: <3.14,>=3.11
License-File: LICENCE.txt
Requires-Dist: torch
Requires-Dist: numpy
Provides-Extra: examples
Requires-Dist: ipykernel; extra == "examples"
Requires-Dist: ipympl; extra == "examples"
Requires-Dist: fairret; extra == "examples"
Requires-Dist: folktables; extra == "examples"
Requires-Dist: scikit-learn; extra == "examples"
Requires-Dist: matplotlib; extra == "examples"
Provides-Extra: benchmark
Requires-Dist: fairret; extra == "benchmark"
Requires-Dist: matplotlib; extra == "benchmark"
Requires-Dist: pandas; extra == "benchmark"
Requires-Dist: folktables; extra == "benchmark"
Requires-Dist: pot; extra == "benchmark"
Requires-Dist: hydra; extra == "benchmark"
Requires-Dist: omegaconf; extra == "benchmark"
Provides-Extra: ghost
Requires-Dist: qpsolvers; extra == "ghost"
Requires-Dist: scipy; extra == "ghost"
Dynamic: license-file
